oremda/clients/__init__.py
oremda/clients/base/__init__.py
oremda/clients/base/client.py
oremda/clients/base/container.py
oremda/clients/base/image.py
oremda/clients/docker/__init__.py
oremda/clients/docker/client.py
oremda/clients/docker/container.py
oremda/clients/docker/image.py
oremda/clients/singularity/__init__.py
oremda/clients/singularity/client.py
oremda/clients/singularity/container.py
oremda/clients/singularity/image.py
oremda/clients/utils.py
oremda/constants.py
oremda/display/__init__.py
oremda/display/matplotlib.py
oremda/event_loops/__init__.py
oremda/event_loops/mpi/__init__.py
oremda/event_loops/mpi/event_loop.py
oremda/event_loops/mpi/non_root_event_loop.py
oremda/event_loops/mpi/root_event_loop.py
oremda/messengers/__init__.py
oremda/messengers/base/__init__.py
oremda/messengers/base/messenger.py
oremda/messengers/mpi/__init__.py
oremda/messengers/mpi/implementations/__init__.py
oremda/messengers/mpi/implementations/thread_multiple.py
oremda/messengers/mpi/implementations/thread_serial.py
oremda/messengers/mpi/messenger.py
oremda/messengers/mqp/__init__.py
oremda/messengers/mqp/messenger.py
oremda/messengers/mqp/utils.py
oremda/models/__init__.py
oremda/pipeline/__init__.py
oremda/pipeline/operator.py
oremda/plasma_client.py
oremda/registry.py
oremda/typing/__init__.py
oremda/utils/__init__.py
oremda/utils/asyncio.py
oremda/utils/concurrency.py
oremda/utils/id.py
oremda/utils/mpi.py
oremda/utils/plasma.py
oremda/utils/singleton.py
oremda/utils/types.py
oremda_core-0.0.2.dist-info/WHEEL
oremda_core-0.0.2.dist-info/METADATA
oremda_core-0.0.2.dist-info/RECORD
