Metadata-Version: 2.1
Name: oremda-core
Version: 0.0.2
Summary: 
License: BSD-3-Clause
Author: Alessandro Genova
Author-email: alessandro.genova@kitware.com
Requires-Python: >=3.8,<4.0
Classifier: License :: OSI Approved :: BSD License
Classifier: Programming Language :: Python :: 3
Classifier: Programming Language :: Python :: 3.10
Classifier: Programming Language :: Python :: 3.8
Classifier: Programming Language :: Python :: 3.9
Requires-Dist: docker (>=5.0.3,<6.0.0)
Requires-Dist: fastapi (>=0.73.0,<0.74.0)
Requires-Dist: matplotlib (>=3.5.1,<4.0.0)
Requires-Dist: numpy (>=1.22.1,<2.0.0)
Requires-Dist: posix-ipc (>=1.0.5,<2.0.0)
Requires-Dist: pyarrow (>=6.0.1,<7.0.0)
Requires-Dist: pydantic (>=1.9.0,<2.0.0)
Requires-Dist: spython (>=0.1.18,<0.2.0)
